{
  "asset": {
    "version": "1.0"
  },
  "geometricError": 2000.0,
  "root": {
    "boundingVolume": {
      "box": [
        -2338.7832500000004,
        -616.3291999999999,
        59.834849999999996,
        2091.58925,
        0.0,
        0.0,
        0.0,
        2878.8136999999997,
        0.0,
        0.0,
        0.0,
        62.06185
      ]
    },
    "geometricError": 2000.0,
    "refine": "REPLACE",
    "children": [
      {
        "boundingVolume": {
          "box": [
            -4221.45625,
            102.84249999999997,
            7.2276500000000006,
            188.0326500000001,
            0.0,
            0.0,
            0.0,
            574.4104,
            0.0,
            0.0,
            0.0,
            8.77965
          ]
        },
        "geometricError": 1000.0,
        "content": {
          "uri": "13_3106_6668.json"
        }
      },
      {
        "boundingVolume": {
          "box": [
            -2217.6947,
            708.49795,
            55.87285,
            1897.5590000000002,
            0.0,
            0.0,
            0.0,
            1553.98655,
            0.0,
            0.0,
            0.0,
            57.29315
          ]
        },
        "geometricError": 1000.0,
        "content": {
          "uri": "13_3106_6669.json"
        }
      },
      {
        "boundingVolume": {
          "box": [
            -4225.3222000000005,
            -2244.0722,
            4.3664,
            205.05030000000011,
            0.0,
            0.0,
            0.0,
            1028.8512999999998,
            0.0,
            0.0,
            0.0,
            6.5934
          ]
        },
        "geometricError": 1000.0,
        "content": {
          "uri": "13_3107_6668.json"
        }
      },
      {
        "boundingVolume": {
          "box": [
            -2182.0185500000002,
            -2083.7655,
            59.863949999999996,
            1934.82455,
            0.0,
            0.0,
            0.0,
            1411.3773999999999,
            0.0,
            0.0,
            0.0,
            62.03275
          ]
        },
        "geometricError": 1000.0,
        "content": {
          "uri": "13_3107_6669.json"
        }
      }
    ]
  }
}