{
  "asset": {
    "version": "1.0"
  },
  "geometricError": 500.0,
  "root": {
    "boundingVolume": {
      "box": [
        -3121.5652,
        251.24620000000004,
        51.443799999999996,
        993.6885000000002,
        0.0,
        0.0,
        0.0,
        951.7028,
        0.0,
        0.0,
        0.0,
        52.7929
      ]
    },
    "geometricError": 500.0,
    "refine": "REPLACE",
    "children": [
      {
        "boundingVolume": {
          "box": [
            -3621.7413,
            722.56,
            11.9832,
            493.51240000000007,
            0.0,
            0.0,
            0.0,
            463.7489,
            0.0,
            0.0,
            0.0,
            13.3232
          ]
        },
        "geometricError": 250.0,
        "content": {
          "uri": "15_12426_26676.json"
        }
      },
      {
        "boundingVolume": {
          "box": [
            -2658.7335000000003,
            740.30625000000009,
            51.68085,
            520.9023,
            0.0,
            0.0,
            0.0,
            462.64275000000004,
            0.0,
            0.0,
            0.0,
            52.55585
          ]
        },
        "geometricError": 250.0,
        "content": {
          "uri": "15_12426_26677.json"
        }
      },
      {
        "boundingVolume": {
          "box": [
            -3631.5253,
            -211.7065,
            18.48215,
            483.67869999999994,
            0.0,
            0.0,
            0.0,
            479.5529,
            0.0,
            0.0,
            0.0,
            19.83125
          ]
        },
        "geometricError": 250.0,
        "content": {
          "uri": "15_12427_26676.json"
        }
      },
      {
        "boundingVolume": {
          "box": [
            -2652.5393999999997,
            -234.95659999999998,
            14.6068,
            524.66270000000009,
            0.0,
            0.0,
            0.0,
            465.5,
            0.0,
            0.0,
            0.0,
            15.428899999999999
          ]
        },
        "geometricError": 250.0,
        "content": {
          "uri": "15_12427_26677.json"
        }
      }
    ]
  }
}