{
  "asset": {
    "version": "1.0"
  },
  "geometricError": 250.0,
  "root": {
    "boundingVolume": {
      "box": [
        3649.1245,
        1611.7418,
        3.072,
        241.9502,
        0.0,
        0.0,
        0.0,
        410.7546,
        0.0,
        0.0,
        0.0,
        4.5736
      ]
    },
    "geometricError": 250.0,
    "refine": "REPLACE",
    "children": [
      {
        "boundingVolume": {
          "box": [
            3658.76765,
            1846.10135,
            0.85804999999999987,
            232.30705000000012,
            0.0,
            0.0,
            0.0,
            176.39504999999997,
            0.0,
            0.0,
            0.0,
            2.35965
          ]
        },
        "geometricError": 0.0,
        "content": {
          "uri": "16_24850_53368.b3dm"
        }
      },
      {
        "boundingVolume": {
          "box": [
            3545.5852,
            1438.0700000000002,
            3.21565,
            138.41089999999986,
            0.0,
            0.0,
            0.0,
            237.08280000000002,
            0.0,
            0.0,
            0.0,
            4.42995
          ]
        },
        "geometricError": 0.0,
        "content": {
          "uri": "16_24851_53368.b3dm"
        }
      }
    ]
  }
}